{
  "DLSVersion": "2.1.6",
  "Name": "J-K FLIP FLOP",
  "NameLocation": 0,
  "ChipType": 0,
  "Size": {
    "x": 1.4,
    "y": 0.75
  },
  "Colour": {
    "r": 0.182344466,
    "g": 0.5950703,
    "b": 0.394104421,
    "a": 1
  },
  "InputPins":[
    {
      "Name":"SET",
      "ID":1180496990,
      "Position":{
        "x":-2.625,
        "y":-4.375
      },
      "BitCount":1,
      "Colour":0,
      "ValueDisplayMode":0
    },
    {
      "Name":"RESET",
      "ID":1421257683,
      "Position":{
        "x":-2.625,
        "y":-5.0
      },
      "BitCount":1,
      "Colour":0,
      "ValueDisplayMode":0
    },
    {
      "Name":"CLOCK",
      "ID":349405989,
      "Position":{
        "x":-2.625,
        "y":-5.8125
      },
      "BitCount":1,
      "Colour":0,
      "ValueDisplayMode":0
    }
  ],
  "OutputPins":[
    {
      "Name":"OUT'",
      "ID":829678591,
      "Position":{
        "x":5.5,
        "y":-4.4375
      },
      "BitCount":1,
      "Colour":0,
      "ValueDisplayMode":0
    },
    {
      "Name":"OUT",
      "ID":1881609778,
      "Position":{
        "x":5.5,
        "y":-4.9375
      },
      "BitCount":1,
      "Colour":0,
      "ValueDisplayMode":0
    }
  ],
  "SubChips":[
    {
      "Name":"S-R LATCH",
      "ID":2106939408,
      "Label":"",
      "Position":{
        "x":2.8975,
        "y":-4.8125
      },
      "OutputPinColourInfo":[{"PinColour":0,"PinID":1651397841},{"PinColour":0,"PinID":1922732438}],
      "InternalData":null
    },
    {
      "Name":"AND-3",
      "ID":1364546486,
      "Label":"",
      "Position":{
        "x":1.5725,
        "y":-4.375
      },
      "OutputPinColourInfo":[{"PinColour":0,"PinID":153375511}],
      "InternalData":null
    },
    {
      "Name":"AND-3",
      "ID":1495169532,
      "Label":"",
      "Position":{
        "x":1.5725,
        "y":-5.25
      },
      "OutputPinColourInfo":[{"PinColour":0,"PinID":153375511}],
      "InternalData":null
    },
    {
      "Name":"PULSE",
      "ID":1299170309,
      "Label":"",
      "Position":{
        "x":-0.24,
        "y":-5.8125
      },
      "OutputPinColourInfo":[{"PinColour":0,"PinID":1}],
      "InternalData":[1,0,0]
    }
  ],
  "Wires":[
    {
      "SourcePinAddress":{
        "PinID":0,
        "PinOwnerID":1421257683
      },
      "TargetPinAddress":{
        "PinID":1857772023,
        "PinOwnerID":1495169532
      },
      "ConnectionType":0,
      "ConnectedWireIndex":-1,
      "ConnectedWireSegmentIndex":-1,
      "Points":[{"x":0.0,"y":0.0},{"x":0.0,"y":0.0}]
    },
    {
      "SourcePinAddress":{
        "PinID":153375511,
        "PinOwnerID":1364546486
      },
      "TargetPinAddress":{
        "PinID":372769903,
        "PinOwnerID":2106939408
      },
      "ConnectionType":0,
      "ConnectedWireIndex":-1,
      "ConnectedWireSegmentIndex":-1,
      "Points":[{"x":0.0,"y":0.0},{"x":0.0,"y":0.0}]
    },
    {
      "SourcePinAddress":{
        "PinID":153375511,
        "PinOwnerID":1495169532
      },
      "TargetPinAddress":{
        "PinID":1572131980,
        "PinOwnerID":2106939408
      },
      "ConnectionType":0,
      "ConnectedWireIndex":-1,
      "ConnectedWireSegmentIndex":-1,
      "Points":[{"x":0.0,"y":0.0},{"x":0.0,"y":0.0}]
    },
    {
      "SourcePinAddress":{
        "PinID":1651397841,
        "PinOwnerID":2106939408
      },
      "TargetPinAddress":{
        "PinID":1857772023,
        "PinOwnerID":1364546486
      },
      "ConnectionType":0,
      "ConnectedWireIndex":-1,
      "ConnectedWireSegmentIndex":-1,
      "Points":[{"x":0.0,"y":0.0},{"x":3.875,"y":-4.6875},{"x":3.875,"y":-3.625},{"x":1.0,"y":-3.625},{"x":1.0,"y":-4.125},{"x":0.0,"y":0.0}]
    },
    {
      "SourcePinAddress":{
        "PinID":1922732438,
        "PinOwnerID":2106939408
      },
      "TargetPinAddress":{
        "PinID":578475341,
        "PinOwnerID":1495169532
      },
      "ConnectionType":0,
      "ConnectedWireIndex":-1,
      "ConnectedWireSegmentIndex":-1,
      "Points":[{"x":0.0,"y":0.0},{"x":3.875,"y":-4.9375},{"x":3.875,"y":-5.75},{"x":1.0,"y":-5.75},{"x":1.0,"y":-5.5},{"x":0.0,"y":0.0}]
    },
    {
      "SourcePinAddress":{
        "PinID":1922732438,
        "PinOwnerID":2106939408
      },
      "TargetPinAddress":{
        "PinID":0,
        "PinOwnerID":1881609778
      },
      "ConnectionType":1,
      "ConnectedWireIndex":4,
      "ConnectedWireSegmentIndex":0,
      "Points":[{"x":3.875,"y":-4.9375},{"x":0.0,"y":0.0}]
    },
    {
      "SourcePinAddress":{
        "PinID":1651397841,
        "PinOwnerID":2106939408
      },
      "TargetPinAddress":{
        "PinID":0,
        "PinOwnerID":829678591
      },
      "ConnectionType":1,
      "ConnectedWireIndex":3,
      "ConnectedWireSegmentIndex":1,
      "Points":[{"x":3.875,"y":-4.4375},{"x":0.0,"y":0.0}]
    },
    {
      "SourcePinAddress":{
        "PinID":1,
        "PinOwnerID":1299170309
      },
      "TargetPinAddress":{
        "PinID":578475341,
        "PinOwnerID":1364546486
      },
      "ConnectionType":0,
      "ConnectedWireIndex":-1,
      "ConnectedWireSegmentIndex":-1,
      "Points":[{"x":0.0,"y":0.0},{"x":0.0,"y":0.0}]
    },
    {
      "SourcePinAddress":{
        "PinID":1,
        "PinOwnerID":1299170309
      },
      "TargetPinAddress":{
        "PinID":1918356613,
        "PinOwnerID":1495169532
      },
      "ConnectionType":0,
      "ConnectedWireIndex":-1,
      "ConnectedWireSegmentIndex":-1,
      "Points":[{"x":0.0,"y":0.0},{"x":0.0,"y":0.0}]
    },
    {
      "SourcePinAddress":{
        "PinID":0,
        "PinOwnerID":349405989
      },
      "TargetPinAddress":{
        "PinID":0,
        "PinOwnerID":1299170309
      },
      "ConnectionType":0,
      "ConnectedWireIndex":-1,
      "ConnectedWireSegmentIndex":-1,
      "Points":[{"x":0.0,"y":0.0},{"x":0.0,"y":0.0}]
    },
    {
      "SourcePinAddress":{
        "PinID":0,
        "PinOwnerID":1180496990
      },
      "TargetPinAddress":{
        "PinID":1918356613,
        "PinOwnerID":1364546486
      },
      "ConnectionType":0,
      "ConnectedWireIndex":-1,
      "ConnectedWireSegmentIndex":-1,
      "Points":[{"x":0.0,"y":0.0},{"x":0.0,"y":0.0}]
    }
  ],
  "Displays": null
}